{
  "metadata": {
    "projectType": "da"
  },
  "templates": [
    {
      "name": "homepage",
      "urls": [
        "https://ultomirishcp.com/"
      ],
      "representativeUrl": "https://ultomirishcp.com/",
      "coverageGaps": [],
      "description": "Homepage with hero indication grid, mechanism-of-action and resources promo cards, support/contact blocks, and Important Safety Information (ISI).",
      "blocks": [
        {
          "name": "hero-banner",
          "instances": ["#content > awt-container:nth-of-type(1)"]
        },
        {
          "name": "cards-indication",
          "instances": ["#content > awt-container:nth-of-type(2)"]
        },
        {
          "name": "columns-media",
          "instances": [
            "#content > awt-container:nth-of-type(4)",
            "#content > awt-container:nth-of-type(5)"
          ]
        },
        {
          "name": "cards-support",
          "instances": ["#content > awt-container:nth-of-type(6)"]
        },
        {
          "name": "cards-contact",
          "instances": ["#awt-container-border-white"]
        },
        {
          "name": "accordion-isi",
          "instances": ["#content > awt-container-warning"]
        },
        {
          "name": "section-quote",
          "instances": ["#content > awt-container:nth-of-type(3)"],
          "section": "accent-teal"
        },
        {
          "name": "section-connect",
          "instances": ["#awt-container-border-white"],
          "section": "warm-orange"
        }
      ],
      "sections": [
        {
          "id": "rc4",
          "name": "Hero banner",
          "selector": "#content > awt-container:nth-of-type(1)",
          "style": null,
          "blocks": ["hero-banner"],
          "defaultContent": []
        },
        {
          "id": "rc5",
          "name": "FDA indications",
          "selector": "#content > awt-container:nth-of-type(2)",
          "style": null,
          "blocks": ["cards-indication"],
          "defaultContent": []
        },
        {
          "id": "rc6",
          "name": "Quote band",
          "selector": "#content > awt-container:nth-of-type(3)",
          "style": "accent-teal",
          "blocks": [],
          "defaultContent": ["#content > awt-container:nth-of-type(3)"]
        },
        {
          "id": "rc7",
          "name": "Mechanism-of-action promo",
          "selector": "#content > awt-container:nth-of-type(4)",
          "style": null,
          "blocks": ["columns-media"],
          "defaultContent": []
        },
        {
          "id": "rc8",
          "name": "Resources promo",
          "selector": "#content > awt-container:nth-of-type(5)",
          "style": null,
          "blocks": ["columns-media"],
          "defaultContent": []
        },
        {
          "id": "rc9",
          "name": "Support cards",
          "selector": "#content > awt-container:nth-of-type(6)",
          "style": null,
          "blocks": ["cards-support"],
          "defaultContent": []
        },
        {
          "id": "rc10",
          "name": "Connect contact band",
          "selector": "#awt-container-border-white",
          "style": "warm-orange",
          "blocks": ["cards-contact"],
          "defaultContent": []
        },
        {
          "id": "rc11",
          "name": "References",
          "selector": "#content > awt-container:nth-of-type(8)",
          "style": null,
          "blocks": [],
          "defaultContent": ["#content > awt-container:nth-of-type(8)"]
        },
        {
          "id": "rc13",
          "name": "Important Safety Information",
          "selector": "#content > awt-container-warning",
          "style": null,
          "blocks": ["accordion-isi"],
          "defaultContent": []
        }
      ]
    },
    {
      "name": "indication-landing",
      "urls": [
        "https://ultomirishcp.com/about-ultomiris",
        "https://ultomirishcp.com/dosing-and-administration",
        "https://ultomirishcp.com/resources-and-support"
      ],
      "representativeUrl": "https://ultomirishcp.com/about-ultomiris",
      "coverageGaps": [],
      "description": "Indication selector landing page with intro heading, 4-card indication grid linking to per-indication subpages, and Important Safety Information (ISI).",
      "blocks": [
        {
          "name": "cards-indication",
          "instances": ["#content > awt-container:nth-of-type(2)"]
        },
        {
          "name": "accordion-isi",
          "instances": ["#content > awt-container-warning"]
        }
      ],
      "sections": [
        {
          "id": "rc4",
          "name": "Intro heading",
          "selector": "#content > awt-container:nth-of-type(1)",
          "style": null,
          "blocks": [],
          "defaultContent": ["#content > awt-container:nth-of-type(1)"]
        },
        {
          "id": "rc5",
          "name": "Indication grid",
          "selector": "#content > awt-container:nth-of-type(2)",
          "style": null,
          "blocks": ["cards-indication"],
          "defaultContent": []
        },
        {
          "id": "rc7",
          "name": "Important Safety Information",
          "selector": "#content > awt-container-warning",
          "style": null,
          "blocks": ["accordion-isi"],
          "defaultContent": []
        }
      ]
    }
  ]
}
